aiocvv/__init__.py
aiocvv/_auth.py
aiocvv/client.py
aiocvv/core.py
aiocvv/dataclasses.py
aiocvv/enums.py
aiocvv/errors.py
aiocvv/me.py
aiocvv/types.py
aiocvv/utils.py
aiocvv/helpers/__init__.py
aiocvv/helpers/noticeboard.py
aiocvv/helpers/calendar/__init__.py
aiocvv/helpers/calendar/core.py
aiocvv/helpers/calendar/period.py
aiocvv/modules/__init__.py
aiocvv/modules/core.py
aiocvv/modules/parents.py
aiocvv/modules/students.py
aiocvv/modules/teachers.py
aiocvv-0.1.1.dist-info/licenses/LICENSE
aiocvv-0.1.1.dist-info/METADATA
aiocvv-0.1.1.dist-info/WHEEL
aiocvv-0.1.1.dist-info/top_level.txt
aiocvv-0.1.1.dist-info/RECORD
