Metadata-Version: 2.4
Name: aiocvv
Version: 0.1.1
Summary: An API wrapper for Classeviva written in Python using asyncio.
Home-page: https://github.com/Vinchethescript/aiocvv
Author: Vinche.zsh
Author-email: vinchethescript@gmail.com
License: GPL-3.0
Requires-Python: >=3.7
License-File: LICENSE
Requires-Dist: aiohttp
Requires-Dist: appdirs
Requires-Dist: bcrypt
Requires-Dist: typing-extensions
Requires-Dist: diskcache
Dynamic: author
Dynamic: author-email
Dynamic: description
Dynamic: description-content-type
Dynamic: home-page
Dynamic: license
Dynamic: license-file
Dynamic: requires-dist
Dynamic: requires-python
Dynamic: summary
